{"stats":{"minecraft:broken":{"mowziesmobs:umvuthana_mask_faith":1,"minecraft:stone_pickaxe":1,"iceandfire:earplugs":1},"minecraft:dropped":{"minecraft:oak_log":15,"minecraft:feather":1,"minecraft:item_frame":1,"minecraft:stick":7,"minecraft:chainmail_leggings":2,"rats:raw_rat":5,"minecraft:bone":2,"minecraft:rotten_flesh":1,"minecraft:bundle":1,"minecraft:oak_sapling":5},"minecraft:killed":{"minecraft:witch":1,"minecraft:horse":4,"minecraft:skeleton":5,"player_companions:rooster":2,"rats:pied_piper":1,"iceandfire:fire_dragon":1,"mowziesmobs:umvuthana":1,"artifacts:mimic":1,"minecraft:pig":1,"rats:rat":6,"minecraft:sheep":1,"minecraft:zombie":18,"minecraft:enderman":1,"minecraft:cow":5},"minecraft:killed_by":{"minecraft:player":1,"iceandfire:cyclops":1,"iceandfire:fire_dragon":1},"minecraft:mined":{"minecraft:tuff":6,"minecraft:granite":2,"minecraft:grass_block":4,"minecraft:coal_block":6,"minecraft:raw_iron_block":32,"minecraft:furnace":1,"minecraft:iron_ore":49,"minecraft:fire":6,"minecraft:andesite":2,"treechop:chopped_log":3,"minecraft:deepslate_lapis_ore":4,"minecraft:bookshelf":1,"minecraft:deepslate_iron_ore":74,"minecraft:iron_bars":2,"minecraft:stone":46,"minecraft:crafting_table":1,"minecraft:torch":1,"minecraft:tall_grass":5,"minecraft:cobblestone":1,"minecraft:lapis_ore":10,"minecraft:sugar_cane":4,"minecraft:diorite":1,"minecraft:bee_nest":1,"minecraft:grass":19,"minecraft:oak_log":10,"minecraft:coal_ore":56,"minecraft:dirt":22,"minecraft:sand":1,"mysticalagriculture:deepslate_prosperity_ore":7,"minecraft:raw_copper_block":6,"create:crimsite":6,"minecraft:deepslate":7},"minecraft:custom":{"minecraft:mob_kills":48,"minecraft:inspect_hopper":1,"minecraft:interact_with_crafting_table":21,"minecraft:open_barrel":11,"goblintraders:trade_with_goblin":1,"minecraft:damage_dealt_resisted":0,"minecraft:leave_game":4,"minecraft:time_since_death":10395,"minecraft:climb_one_cm":455,"minecraft:damage_resisted":0,"minecraft:sprint_one_cm":116883,"minecraft:walk_one_cm":119277,"minecraft:damage_blocked_by_shield":250,"minecraft:drop":40,"minecraft:play_time":82102,"minecraft:deaths":3,"minecraft:sneak_time":656,"minecraft:walk_under_water_one_cm":5751,"minecraft:jump":1025,"minecraft:walk_on_water_one_cm":4458,"minecraft:total_world_time":82102,"minecraft:interact_with_furnace":10,"tombstone:raider_killed":1,"minecraft:sleep_in_bed":1,"minecraft:time_since_rest":10420,"minecraft:damage_taken":3303,"minecraft:trigger_trapped_chest":4,"minecraft:damage_dealt":9814,"minecraft:swim_one_cm":1000,"minecraft:fly_one_cm":202392,"minecraft:open_chest":16,"minecraft:crouch_one_cm":377,"waystones:waystone_activated":1,"tombstone:undead_killed":23,"minecraft:fall_one_cm":19295},"minecraft:crafted":{"minecraft:oak_planks":76,"minecraft:raw_iron":282,"minecraft:furnace":2,"minecraft:hopper":1,"minecraft:raw_copper":45,"minecraft:iron_boots":1,"minecraft:stone_pickaxe":1,"minecraft:crafting_table":3,"minecraft:wooden_pickaxe":1,"iceandfire:earplugs":1,"minecraft:stone_axe":1,"minecraft:air":0,"minecraft:stick":4,"minecraft:iron_ingot":11,"minecraft:iron_pickaxe":1,"minecraft:torch":20},"minecraft:picked_up":{"minecraft:crafting_table":1,"croptopia:peach":1,"minecraft:enchanted_book":1,"rats:rat_paw":1,"minecraft:item_frame":1,"minecraft:iron_shovel":1,"mysticalagriculture:inferium_essence":9,"minecraft:cobbled_deepslate":9,"minecraft:beef":8,"minecraft:sugar_cane":9,"minecraft:coal_block":6,"minecraft:furnace":1,"minecraft:raw_copper_block":5,"minecraft:egg":1,"iceandfire:dragonbone":11,"minecraft:stick":14,"minecraft:raw_iron":167,"iceandfire:dragonscales_green":15,"apotheosis:gem":1,"minecraft:torch":2,"mysticalagriculture:prosperity_shard":23,"sophisticatedbackpacks:backpack":1,"minecraft:porkchop":1,"minecraft:stone_button":1,"tombstone:grave_dust":2,"minecraft:diorite":2,"rats:pied_wool":1,"minecraft:arrow":3,"minecraft:rotten_flesh":18,"iceandfire:fire_dragon_heart":1,"minecraft:mutton":1,"minecraft:iron_bars":2,"minecraft:white_wool":1,"minecraft:bone_block":11,"minecraft:cobblestone":46,"minecraft:oxeye_daisy":1,"minecraft:feather":3,"artifacts:eternal_steak":2,"minecraft:andesite":2,"minecraft:leather":5,"minecraft:potato":2,"minecraft:tuff":5,"minecraft:oak_log":36,"minecraft:chainmail_chestplate":1,"rats:rat_pelt":4,"rats:raw_rat":6,"minecraft:lapis_lazuli":87,"minecraft:dirt":25,"minecraft:name_tag":1,"minecraft:bone":6,"minecraft:apple":1,"mowziesmobs:umvuthana_mask_rage":1,"minecraft:wheat_seeds":4,"minecraft:raw_gold":4,"minecraft:iron_ingot":1,"artifacts:whoopee_cushion":1,"minecraft:glowstone_dust":2,"iceandfire:fire_dragon_flesh":5,"croptopia:kiwi":1,"croptopia:starfruit":1,"minecraft:raw_iron_block":40,"croptopia:hops":1,"minecraft:sand":1,"minecraft:bundle":2,"croptopia:hops_seed":2,"create:crimsite":5,"artifacts:crystal_heart":1,"minecraft:chainmail_leggings":3,"croptopia:orange":1,"minecraft:granite":3,"tombstone:magic_scroll":2,"minecraft:oak_sapling":10,"minecraft:coal":51},"minecraft:used":{"croptopia:starfruit":1,"minecraft:shield":52,"minecraft:rotten_flesh":3,"minecraft:torch":9,"minecraft:dirt":6,"minecraft:mutton":1,"minecraft:hopper":1,"simplyswords:diamond_longsword":116,"artifacts:mimic_spawn_egg":1,"minecraft:rabbit_stew":1,"iceandfire:earplugs":1,"mowziesmobs:umvuthana_mask_rage":1,"minecraft:beef":2,"minecraft:furnace":2,"tombstone:gift":4,"minecraft:egg":1,"minecraft:potato":2,"minecraft:stone_pickaxe":131,"minecraft:oak_planks":11,"minecraft:wooden_pickaxe":23,"artifacts:eternal_steak":17,"minecraft:diamond_axe":11,"minecraft:cookie":1,"minecraft:crafting_table":3,"minecraft:mushroom_stew":1,"croptopia:orange":1,"rats:raw_rat":1,"minecraft:apple":1,"minecraft:iron_pickaxe":179,"tombstone:magic_scroll":1,"minecraft:stone_axe":55,"minecraft:coal_block":1,"minecraft:cobblestone":4,"croptopia:kiwi":1,"minecraft:porkchop":1,"minecraft:cooked_porkchop":1,"minecraft:andesite":2}},"DataVersion":3465}